equi7grid_lite/__init__.py
equi7grid_lite/data/metadata.pkl
equi7grid_lite/dataclass.py
equi7grid_lite/main.py
equi7grid_lite/utils.py
equi7grid_lite-0.6.0.dist-info/LICENSE
equi7grid_lite-0.6.0.dist-info/WHEEL
equi7grid_lite-0.6.0.dist-info/METADATA
equi7grid_lite-0.6.0.dist-info/RECORD
