Metadata-Version: 2.1
Name: equi7grid-lite
Version: 0.6.0
Summary: A user-friendly Python interface to interact with the Equi7Grid grid system
Home-page: https://github.com/csaybar/equi7grid-lite
Author: Cesar Aybar
Author-email: cesar.aybar@uv.es
Requires-Python: >=3.9,<4.0
Classifier: Programming Language :: Python :: 3
Classifier: Programming Language :: Python :: 3.9
Classifier: Programming Language :: Python :: 3.10
Requires-Dist: geopandas (>=0.13.2)
Requires-Dist: nptyping (>=2.5.0)
Requires-Dist: numpy (>=1.25.2)
Requires-Dist: pandas (>=2.0.3)
Requires-Dist: shapely (>=2.0.4)
Project-URL: Documentation, https://ipl-uv.github.io/equi7grid-lite/
Project-URL: Repository, https://github.com/csaybar/equi7grid-lite
